spin/__init__.py
spin/neighborhood_spin.py
spin/side_to_side_spin.py
spin/utils.py
spin/distances/__init__.py
spin/distances/distances.py
spin/distances/tests/__init__.py
spin/distances/tests/random_vectors.py
spin/distances/tests/test_distances.py
spin/tests/__init__.py
spin/tests/data_utils.py
spin/tests/test_neighborhood_spin.py
spin/tests/test_side_to_side_spin.py
spin/tests/test_spin.py
spin/tests/test_utils.py
spin_clustering-0.1.0.dist-info/LICENSE
spin_clustering-0.1.0.dist-info/METADATA
spin_clustering-0.1.0.dist-info/WHEEL
spin_clustering-0.1.0.dist-info/top_level.txt
spin_clustering-0.1.0.dist-info/RECORD
