Metadata-Version: 2.1
Name: spin-clustering
Version: 0.1.0
Summary: SPIN clustering method package.
Home-page: UNKNOWN
Maintainer: otaviocv
Maintainer-email: otaviocv.deluqui@gmail.com
License: MIT
Platform: UNKNOWN
Requires-Python: >=3.6
Requires-Dist: numpy (>=1.16.4)
Requires-Dist: matplotlib (>=3.1.0)
